json2toon/__init__.py
json2toon/analyzer.py
json2toon/cli.py
json2toon/config.py
json2toon/core.py
json2toon/decoder.py
json2toon/encoder.py
json2toon/exceptions.py
json2toon/metrics.py
json2toon/prompt.py
py_json2toon-0.1.0.dist-info/licenses/LICENSE
py_json2toon-0.1.0.dist-info/METADATA
py_json2toon-0.1.0.dist-info/WHEEL
py_json2toon-0.1.0.dist-info/entry_points.txt
py_json2toon-0.1.0.dist-info/top_level.txt
py_json2toon-0.1.0.dist-info/RECORD
