Metadata-Version: 2.4
Name: py-json2toon
Version: 0.1.0
Summary: Convert JSON structures into TOON (Token-Oriented Object Notation) for LLM-friendly prompts
Author: json2toon Team
License: MIT
Project-URL: Homepage, https://github.com/Idk507/json2toon
Project-URL: Documentation, https://github.com/Idk507/json2toon#readme
Project-URL: Repository, https://github.com/Idk507/json2toon
Project-URL: Issues, https://github.com/Idk507/json2toon/issues
Keywords: json,toon,llm,token-optimization,prompt-engineering
Classifier: Development Status :: 3 - Alpha
Classifier: Intended Audience :: Developers
Classifier: License :: OSI Approved :: MIT License
Classifier: Programming Language :: Python :: 3
Classifier: Programming Language :: Python :: 3.8
Classifier: Programming Language :: Python :: 3.9
Classifier: Programming Language :: Python :: 3.10
Classifier: Programming Language :: Python :: 3.11
Classifier: Programming Language :: Python :: 3.12
Classifier: Topic :: Software Development :: Libraries :: Python Modules
Classifier: Topic :: Text Processing :: Markup
Requires-Python: >=3.8
License-File: LICENSE
Requires-Dist: tiktoken>=0.5.0
Requires-Dist: typer>=0.9.0
Requires-Dist: rich>=13.0.0
Provides-Extra: dev
Requires-Dist: pytest>=7.0.0; extra == "dev"
Requires-Dist: pytest-cov>=4.0.0; extra == "dev"
Requires-Dist: black>=23.0.0; extra == "dev"
Requires-Dist: mypy>=1.0.0; extra == "dev"
Requires-Dist: isort>=5.12.0; extra == "dev"
Requires-Dist: flake8>=6.0.0; extra == "dev"
Dynamic: license-file
